blackboxopt/__init__.py
blackboxopt/base.py
blackboxopt/evaluation.py
blackboxopt/examples/__init__.py
blackboxopt/examples/dask_distributed.py
blackboxopt/examples/multi_objective_multi_param.py
blackboxopt/io.py
blackboxopt/logger.py
blackboxopt/optimization_loops/__init__.py
blackboxopt/optimization_loops/dask_distributed.py
blackboxopt/optimization_loops/file_based_distributed.py
blackboxopt/optimization_loops/sequential.py
blackboxopt/optimization_loops/testing.py
blackboxopt/optimization_loops/utils.py
blackboxopt/optimizers/__init__.py
blackboxopt/optimizers/bohb.py
blackboxopt/optimizers/botorch_base.py
blackboxopt/optimizers/botorch_utils.py
blackboxopt/optimizers/hyperband.py
blackboxopt/optimizers/random_search.py
blackboxopt/optimizers/space_filling.py
blackboxopt/optimizers/staged/__init__.py
blackboxopt/optimizers/staged/bohb.py
blackboxopt/optimizers/staged/configuration_sampler.py
blackboxopt/optimizers/staged/hyperband.py
blackboxopt/optimizers/staged/iteration.py
blackboxopt/optimizers/staged/optimizer.py
blackboxopt/optimizers/staged/utils.py
blackboxopt/optimizers/testing.py
blackboxopt/py.typed
blackboxopt/utils.py
blackboxopt/visualizations/__init__.py
blackboxopt/visualizations/to_html_patch.js
blackboxopt/visualizations/utils.py
blackboxopt/visualizations/visualizer.py
blackboxopt-5.3.4.dist-info/METADATA
blackboxopt-5.3.4.dist-info/WHEEL
blackboxopt-5.3.4.dist-info/licenses/LICENSE
blackboxopt-5.3.4.dist-info/licenses/NOTICE
blackboxopt-5.3.4.dist-info/RECORD
