Metadata-Version: 2.4
Name: blackboxopt
Version: 5.3.4
Summary: A common interface for blackbox optimization algorithms along with useful helpers like parallel optimization loops, analysis and visualization scripts.
License: Apache-2.0
License-File: LICENSE
License-File: NOTICE
Author: Bosch Center for AI, Robert Bosch GmbH
Requires-Python: >=3.10,<3.15
Classifier: License :: OSI Approved :: Apache Software License
Classifier: Programming Language :: Python :: 3
Classifier: Programming Language :: Python :: 3.10
Classifier: Programming Language :: Python :: 3.11
Classifier: Programming Language :: Python :: 3.12
Classifier: Programming Language :: Python :: 3.13
Classifier: Programming Language :: Python :: 3.14
Provides-Extra: all
Provides-Extra: bohb
Provides-Extra: botorch
Provides-Extra: dask
Provides-Extra: examples
Provides-Extra: hyperband
Provides-Extra: space-fill
Provides-Extra: testing
Provides-Extra: visualization
Requires-Dist: botorch (>=0.7.1) ; extra == "all" or extra == "botorch"
Requires-Dist: dask (>=2023.1.0,<2024.0.0) ; extra == "all" or extra == "dask" or extra == "examples"
Requires-Dist: distributed (>=2023.1.0,<2024.0.0) ; extra == "all" or extra == "dask" or extra == "examples"
Requires-Dist: pandas (>=2.2.2,<3.0.0) ; extra == "all" or extra == "visualization"
Requires-Dist: parameterspace (>=0.7.2)
Requires-Dist: plotly (>=5.10.0,<6.0.0) ; extra == "all" or extra == "visualization"
Requires-Dist: pymoo (>=0.5,<1.0) ; extra == "all" or extra == "visualization"
Requires-Dist: scipy (>=1.14.0,<2.0.0) ; (python_version < "3.14") and (extra == "all" or extra == "bohb" or extra == "space-fill" or extra == "visualization")
Requires-Dist: scipy (>=1.16.1,<2.0.0) ; (python_version >= "3.14") and (extra == "all" or extra == "bohb" or extra == "space-fill" or extra == "visualization")
Requires-Dist: statsmodels (>=0.14.2,<0.15.0) ; extra == "all" or extra == "bohb"
Requires-Dist: sympy (>=1.12,<2.0) ; extra == "all" or extra == "botorch"
Requires-Dist: torch (>=2.3) ; extra == "all" or extra == "botorch"
Project-URL: Repository, https://github.com/boschresearch/blackboxopt
